primitive_tts/__init__.py
primitive_tts/en.py
primitive_tts/speech.py
primitive_tts-0.0.1.dist-info/METADATA
primitive_tts-0.0.1.dist-info/WHEEL
primitive_tts-0.0.1.dist-info/licenses/LICENSE
primitive_tts-0.0.1.dist-info/RECORD
