Metadata-Version: 2.4
Name: primitive-tts
Version: 0.0.1
Summary: A simple text-to-speech library
Project-URL: Repository, https://github.com/gunthercox/primitive-tts.git
Author: Gunther Cox
License: MIT
License-File: LICENSE
Keywords: speech,speech synthesis,text-to-speech,tts
Classifier: Development Status :: 4 - Beta
Classifier: Natural Language :: English
Classifier: Topic :: Multimedia :: Sound/Audio :: Sound Synthesis
Classifier: Topic :: Multimedia :: Sound/Audio :: Speech
Requires-Python: >=3.4
Provides-Extra: sounddevice
Requires-Dist: sounddevice; extra == 'sounddevice'
